{
  "id": "217",
  "title": "奇怪的线段树",
  "type": "traditional",
  "sections": [
    {
      "title": "",
      "content": "\u003cp\u003esylvia 是一个热爱学习的女孩子，今天她想要学习线段树技巧。\u003c/p\u003e\u003cp\u003e但是因为 sylvia 是还是萌新，所以她一不小心将线段树写成了奇怪的形状：\u003c/p\u003e\u003cp\u003e在正常的线段树中，对于区间 \u003cspan class=\"MathJax_Preview\" style=\"color: inherit;\"\u003e\u003cspan class=\"MJXp-math\" id=\"MJXp-Span-1\"\u003e\u003cspan class=\"MJXp-mo\" id=\"MJXp-Span-2\" style=\"margin-left: 0em; margin-right: 0em;\"\u003e[\u003c/span\u003e\u003cspan class=\"MJXp-mi MJXp-italic\" id=\"MJXp-Span-3\"\u003el\u003c/span\u003e\u003cspan class=\"MJXp-mo\" id=\"MJXp-Span-4\" style=\"margin-left: 0em; margin-right: 0.222em;\"\u003e,\u003c/span\u003e\u003cspan class=\"MJXp-mi MJXp-italic\" id=\"MJXp-Span-5\"\u003er\u003c/span\u003e\u003cspan class=\"MJXp-mo\" id=\"MJXp-Span-6\" style=\"margin-left: 0em; margin-right: 0em;\"\u003e]\u003c/span\u003e\u003c/span\u003e\u003c/span\u003e\u003cscript type=\"math/tex\" id=\"MathJax-Element-1\"\u003e[l,r]\u003c/script\u003e，我们会取 \u003cspan class=\"MathJax_Preview\" style=\"color: inherit;\"\u003e\u003cspan class=\"MJXp-math\" id=\"MJXp-Span-7\"\u003e\u003cspan class=\"MJXp-mi MJXp-italic\" id=\"MJXp-Span-8\"\u003em\u003c/span\u003e\u003cspan class=\"MJXp-mo\" id=\"MJXp-Span-9\" style=\"margin-left: 0.333em; margin-right: 0.333em;\"\u003e=\u003c/span\u003e\u003cspan class=\"MJXp-mo\" id=\"MJXp-Span-10\" style=\"margin-left: 0em; margin-right: 0em;\"\u003e⌊\u003c/span\u003e\u003cspan class=\"MJXp-mfrac\" id=\"MJXp-Span-11\" style=\"vertical-align: 0.25em;\"\u003e\u003cspan class=\"MJXp-box MJXp-script\"\u003e\u003cspan class=\"MJXp-mi MJXp-italic\" id=\"MJXp-Span-12\"\u003el\u003c/span\u003e\u003cspan class=\"MJXp-mo\" id=\"MJXp-Span-13\"\u003e+\u003c/span\u003e\u003cspan class=\"MJXp-mi MJXp-italic\" id=\"MJXp-Span-14\"\u003er\u003c/span\u003e\u003c/span\u003e\u003cspan class=\"MJXp-box\" style=\"margin-top: -0.9em;\"\u003e\u003cspan class=\"MJXp-denom\"\u003e\u003cspan\u003e\u003cspan class=\"MJXp-rule\" style=\"height: 1em; border-top: none; border-bottom: 1px solid; margin: 0.1em 0px;\"\u003e\u003c/span\u003e\u003c/span\u003e\u003cspan\u003e\u003cspan class=\"MJXp-box MJXp-script\"\u003e\u003cspan class=\"MJXp-mn\" id=\"MJXp-Span-15\"\u003e2\u003c/span\u003e\u003c/span\u003e\u003c/span\u003e\u003c/span\u003e\u003c/span\u003e\u003c/span\u003e\u003cspan class=\"MJXp-mo\" id=\"MJXp-Span-16\" style=\"margin-left: 0em; margin-right: 0em;\"\u003e⌋\u003c/span\u003e\u003c/span\u003e\u003c/span\u003e\u003cscript type=\"math/tex\" id=\"MathJax-Element-2\"\u003em=\\lfloor \\frac{l+r}{2} \\rfloor\u003c/script\u003e，然后将这个区间分成 \u003cspan class=\"MathJax_Preview\" style=\"color: inherit;\"\u003e\u003cspan class=\"MJXp-math\" id=\"MJXp-Span-17\"\u003e\u003cspan class=\"MJXp-mo\" id=\"MJXp-Span-18\" style=\"margin-left: 0em; margin-right: 0em;\"\u003e[\u003c/span\u003e\u003cspan class=\"MJXp-mi MJXp-italic\" id=\"MJXp-Span-19\"\u003el\u003c/span\u003e\u003cspan class=\"MJXp-mo\" id=\"MJXp-Span-20\" style=\"margin-left: 0em; margin-right: 0.222em;\"\u003e,\u003c/span\u003e\u003cspan class=\"MJXp-mi MJXp-italic\" id=\"MJXp-Span-21\"\u003em\u003c/span\u003e\u003cspan class=\"MJXp-mo\" id=\"MJXp-Span-22\" style=\"margin-left: 0em; margin-right: 0em;\"\u003e]\u003c/span\u003e\u003c/span\u003e\u003c/span\u003e\u003cscript type=\"math/tex\" id=\"MathJax-Element-3\"\u003e[l,m]\u003c/script\u003e 和 \u003cspan class=\"MathJax_Preview\" style=\"color: inherit;\"\u003e\u003cspan class=\"MJXp-math\" id=\"MJXp-Span-23\"\u003e\u003cspan class=\"MJXp-mo\" id=\"MJXp-Span-24\" style=\"margin-left: 0em; margin-right: 0em;\"\u003e[\u003c/span\u003e\u003cspan class=\"MJXp-mi MJXp-italic\" id=\"MJXp-Span-25\"\u003em\u003c/span\u003e\u003cspan class=\"MJXp-mo\" id=\"MJXp-Span-26\" style=\"margin-left: 0.267em; margin-right: 0.267em;\"\u003e+\u003c/span\u003e\u003cspan class=\"MJXp-mn\" id=\"MJXp-Span-27\"\u003e1\u003c/span\u003e\u003cspan class=\"MJXp-mo\" id=\"MJXp-Span-28\" style=\"margin-left: 0em; margin-right: 0.222em;\"\u003e,\u003c/span\u003e\u003cspan class=\"MJXp-mi MJXp-italic\" id=\"MJXp-Span-29\"\u003er\u003c/span\u003e\u003cspan class=\"MJXp-mo\" id=\"MJXp-Span-30\" style=\"margin-left: 0em; margin-right: 0em;\"\u003e]\u003c/span\u003e\u003c/span\u003e\u003c/span\u003e\u003cscript type=\"math/tex\" id=\"MathJax-Element-4\"\u003e[m+1,r]\u003c/script\u003e 两个子区间。\u003c/p\u003e\u003cp\u003e但是，sylvia 的线段树却不是这样的，她用了一种不可描述的方式取了 \u003cspan class=\"MathJax_Preview\" style=\"color: inherit;\"\u003e\u003cspan class=\"MJXp-math\" id=\"MJXp-Span-31\"\u003e\u003cspan class=\"MJXp-mi MJXp-italic\" id=\"MJXp-Span-32\"\u003em\u003c/span\u003e\u003c/span\u003e\u003c/span\u003e\u003cscript type=\"math/tex\" id=\"MathJax-Element-5\"\u003em\u003c/script\u003e 的值（当然 \u003cspan class=\"MathJax_Preview\" style=\"color: inherit;\"\u003e\u003cspan class=\"MJXp-math\" id=\"MJXp-Span-33\"\u003e\u003cspan class=\"MJXp-mi MJXp-italic\" id=\"MJXp-Span-34\"\u003em\u003c/span\u003e\u003c/span\u003e\u003c/span\u003e\u003cscript type=\"math/tex\" id=\"MathJax-Element-6\"\u003em\u003c/script\u003e 还是满足 \u003cspan class=\"MathJax_Preview\" style=\"color: inherit;\"\u003e\u003cspan class=\"MJXp-math\" id=\"MJXp-Span-35\"\u003e\u003cspan class=\"MJXp-mi MJXp-italic\" id=\"MJXp-Span-36\"\u003el\u003c/span\u003e\u003cspan class=\"MJXp-mo\" id=\"MJXp-Span-37\" style=\"margin-left: 0.333em; margin-right: 0.333em;\"\u003e≤\u003c/span\u003e\u003cspan class=\"MJXp-mi MJXp-italic\" id=\"MJXp-Span-38\"\u003em\u003c/span\u003e\u003cspan class=\"MJXp-mo\" id=\"MJXp-Span-39\" style=\"margin-left: 0.333em; margin-right: 0.333em;\"\u003e\u0026lt;\u003c/span\u003e\u003cspan class=\"MJXp-mi MJXp-italic\" id=\"MJXp-Span-40\"\u003er\u003c/span\u003e\u003c/span\u003e\u003c/span\u003e\u003cscript type=\"math/tex\" id=\"MathJax-Element-7\"\u003el \\leq m \u003c r\u003c/script\u003e 的），以至于整棵树的形状非常奇怪。\u003c/p\u003e\u003cp\u003e奇怪归奇怪，这棵线段树仍然是可以进行线段树的操作的，就比如下面这棵在 \u003cspan class=\"MathJax_Preview\" style=\"color: inherit;\"\u003e\u003cspan class=\"MJXp-math\" id=\"MJXp-Span-41\"\u003e\u003cspan class=\"MJXp-mo\" id=\"MJXp-Span-42\" style=\"margin-left: 0em; margin-right: 0em;\"\u003e[\u003c/span\u003e\u003cspan class=\"MJXp-mn\" id=\"MJXp-Span-43\"\u003e1\u003c/span\u003e\u003cspan class=\"MJXp-mo\" id=\"MJXp-Span-44\" style=\"margin-left: 0em; margin-right: 0.222em;\"\u003e,\u003c/span\u003e\u003cspan class=\"MJXp-mn\" id=\"MJXp-Span-45\"\u003e6\u003c/span\u003e\u003cspan class=\"MJXp-mo\" id=\"MJXp-Span-46\" style=\"margin-left: 0em; margin-right: 0em;\"\u003e]\u003c/span\u003e\u003c/span\u003e\u003c/span\u003e\u003cscript type=\"math/tex\" id=\"MathJax-Element-8\"\u003e[1,6]\u003c/script\u003e 上建的奇怪的线段树，我们仍然可以用传统的线段树算法定位出一些区间（只不过不再满足 \u003cspan class=\"MathJax_Preview\" style=\"color: inherit;\"\u003e\u003cspan class=\"MJXp-math\" id=\"MJXp-Span-47\"\u003e\u003cspan class=\"MJXp-mi\" id=\"MJXp-Span-48\"\u003elog\u003c/span\u003e\u003c/span\u003e\u003c/span\u003e\u003cscript type=\"math/tex\" id=\"MathJax-Element-9\"\u003e\\log\u003c/script\u003e 的复杂度了），以区间 \u003cspan class=\"MathJax_Preview\" style=\"color: inherit;\"\u003e\u003cspan class=\"MJXp-math\" id=\"MJXp-Span-49\"\u003e\u003cspan class=\"MJXp-mo\" id=\"MJXp-Span-50\" style=\"margin-left: 0em; margin-right: 0em;\"\u003e[\u003c/span\u003e\u003cspan class=\"MJXp-mn\" id=\"MJXp-Span-51\"\u003e2\u003c/span\u003e\u003cspan class=\"MJXp-mo\" id=\"MJXp-Span-52\" style=\"margin-left: 0em; margin-right: 0.222em;\"\u003e,\u003c/span\u003e\u003cspan class=\"MJXp-mn\" id=\"MJXp-Span-53\"\u003e4\u003c/span\u003e\u003cspan class=\"MJXp-mo\" id=\"MJXp-Span-54\" style=\"margin-left: 0em; margin-right: 0em;\"\u003e]\u003c/span\u003e\u003c/span\u003e\u003c/span\u003e\u003cscript type=\"math/tex\" id=\"MathJax-Element-10\"\u003e[2,4]\u003c/script\u003e 为例，那么定位的过程如蓝色箭头所示，经过的节点为蓝色节点。\u003c/p\u003e\u003cp\u003e\u003cimg class=\"img-responsive center-block\" src=\"//img.uoj.ac/utility/seg.png\" alt=\"线段树\"\u003e\u003c/p\u003e\u003cp\u003e现在 sylvia 建出了一棵奇怪的线段树，最开始所有点都是白色的。接着 sylvia 对这棵线段树进行了若干次操作，每次操作都给出了一个区间 \u003cspan class=\"MathJax_Preview\" style=\"color: inherit;\"\u003e\u003cspan class=\"MJXp-math\" id=\"MJXp-Span-55\"\u003e\u003cspan class=\"MJXp-mo\" id=\"MJXp-Span-56\" style=\"margin-left: 0em; margin-right: 0em;\"\u003e[\u003c/span\u003e\u003cspan class=\"MJXp-mi MJXp-italic\" id=\"MJXp-Span-57\"\u003el\u003c/span\u003e\u003cspan class=\"MJXp-mo\" id=\"MJXp-Span-58\" style=\"margin-left: 0em; margin-right: 0.222em;\"\u003e,\u003c/span\u003e\u003cspan class=\"MJXp-mi MJXp-italic\" id=\"MJXp-Span-59\"\u003er\u003c/span\u003e\u003cspan class=\"MJXp-mo\" id=\"MJXp-Span-60\" style=\"margin-left: 0em; margin-right: 0em;\"\u003e]\u003c/span\u003e\u003c/span\u003e\u003c/span\u003e\u003cscript type=\"math/tex\" id=\"MathJax-Element-11\"\u003e[l,r]\u003c/script\u003e 并在线段树上定位出这个区间，在定位的同时，它把经过的节点都染黑了（本来就是黑的节点仍然保持黑色）。\u003c/p\u003e\u003cp\u003e例如对上面这棵线段树，第一次操作为 \u003cspan class=\"MathJax_Preview\" style=\"color: inherit;\"\u003e\u003cspan class=\"MJXp-math\" id=\"MJXp-Span-61\"\u003e\u003cspan class=\"MJXp-mo\" id=\"MJXp-Span-62\" style=\"margin-left: 0em; margin-right: 0em;\"\u003e[\u003c/span\u003e\u003cspan class=\"MJXp-mn\" id=\"MJXp-Span-63\"\u003e2\u003c/span\u003e\u003cspan class=\"MJXp-mo\" id=\"MJXp-Span-64\" style=\"margin-left: 0em; margin-right: 0.222em;\"\u003e,\u003c/span\u003e\u003cspan class=\"MJXp-mn\" id=\"MJXp-Span-65\"\u003e4\u003c/span\u003e\u003cspan class=\"MJXp-mo\" id=\"MJXp-Span-66\" style=\"margin-left: 0em; margin-right: 0em;\"\u003e]\u003c/span\u003e\u003c/span\u003e\u003c/span\u003e\u003cscript type=\"math/tex\" id=\"MathJax-Element-12\"\u003e[2,4]\u003c/script\u003e，那么在操作后所有蓝色节点都被染黑了。\u003c/p\u003e\u003cp\u003e但是因为 sylvia 是一个健忘的女孩子，过了一段时间后，她已经忘了她到底进行了哪些操作，但是幸运的是最终的线段树还是被保留了下来。\u003c/p\u003e\u003cp\u003e现在 sylvia 想要知道她最少进行多少次操作，才能将本来全白的线段树变成现在这样。\u003c/p\u003e",
      "misc": ""
    },
    {
      "title": "输入格式",
      "content": "\u003cp\u003e输入第一行一个正整数 \u003cspan class=\"MathJax_Preview\" style=\"color: inherit;\"\u003e\u003cspan class=\"MJXp-math\" id=\"MJXp-Span-67\"\u003e\u003cspan class=\"MJXp-mi MJXp-italic\" id=\"MJXp-Span-68\"\u003en\u003c/span\u003e\u003c/span\u003e\u003c/span\u003e\u003cscript type=\"math/tex\" id=\"MathJax-Element-13\"\u003en\u003c/script\u003e 表示线段树的根节点为 \u003cspan class=\"MathJax_Preview\" style=\"color: inherit;\"\u003e\u003cspan class=\"MJXp-math\" id=\"MJXp-Span-69\"\u003e\u003cspan class=\"MJXp-mo\" id=\"MJXp-Span-70\" style=\"margin-left: 0em; margin-right: 0em;\"\u003e[\u003c/span\u003e\u003cspan class=\"MJXp-mn\" id=\"MJXp-Span-71\"\u003e1\u003c/span\u003e\u003cspan class=\"MJXp-mo\" id=\"MJXp-Span-72\" style=\"margin-left: 0em; margin-right: 0.222em;\"\u003e,\u003c/span\u003e\u003cspan class=\"MJXp-mi MJXp-italic\" id=\"MJXp-Span-73\"\u003en\u003c/span\u003e\u003cspan class=\"MJXp-mo\" id=\"MJXp-Span-74\" style=\"margin-left: 0em; margin-right: 0em;\"\u003e]\u003c/span\u003e\u003c/span\u003e\u003c/span\u003e\u003cscript type=\"math/tex\" id=\"MathJax-Element-14\"\u003e[1,n]\u003c/script\u003e。\u003c/p\u003e\u003cp\u003e接下来 \u003cspan class=\"MathJax_Preview\" style=\"color: inherit;\"\u003e\u003cspan class=\"MJXp-math\" id=\"MJXp-Span-75\"\u003e\u003cspan class=\"MJXp-mn\" id=\"MJXp-Span-76\"\u003e2\u003c/span\u003e\u003cspan class=\"MJXp-mi MJXp-italic\" id=\"MJXp-Span-77\"\u003en\u003c/span\u003e\u003cspan class=\"MJXp-mo\" id=\"MJXp-Span-78\" style=\"margin-left: 0.267em; margin-right: 0.267em;\"\u003e−\u003c/span\u003e\u003cspan class=\"MJXp-mn\" id=\"MJXp-Span-79\"\u003e1\u003c/span\u003e\u003c/span\u003e\u003c/span\u003e\u003cscript type=\"math/tex\" id=\"MathJax-Element-15\"\u003e2n-1\u003c/script\u003e 行按照线段树的先序遍历描述了每一个节点，如果这个节点是叶子节点，那么这一行只有一个整数 \u003cspan class=\"MathJax_Preview\" style=\"color: inherit;\"\u003e\u003cspan class=\"MJXp-math\" id=\"MJXp-Span-80\"\u003e\u003cspan class=\"MJXp-msubsup\" id=\"MJXp-Span-81\"\u003e\u003cspan class=\"MJXp-mi MJXp-italic\" id=\"MJXp-Span-82\" style=\"margin-right: 0.05em;\"\u003et\u003c/span\u003e\u003cspan class=\"MJXp-mi MJXp-italic MJXp-script\" id=\"MJXp-Span-83\" style=\"vertical-align: -0.4em;\"\u003ei\u003c/span\u003e\u003c/span\u003e\u003c/span\u003e\u003c/span\u003e\u003cscript type=\"math/tex\" id=\"MathJax-Element-16\"\u003et_i\u003c/script\u003e，否则这一行有两个整数 \u003cspan class=\"MathJax_Preview\" style=\"color: inherit;\"\u003e\u003cspan class=\"MJXp-math\" id=\"MJXp-Span-84\"\u003e\u003cspan class=\"MJXp-msubsup\" id=\"MJXp-Span-85\"\u003e\u003cspan class=\"MJXp-mi MJXp-italic\" id=\"MJXp-Span-86\" style=\"margin-right: 0.05em;\"\u003et\u003c/span\u003e\u003cspan class=\"MJXp-mi MJXp-italic MJXp-script\" id=\"MJXp-Span-87\" style=\"vertical-align: -0.4em;\"\u003ei\u003c/span\u003e\u003c/span\u003e\u003c/span\u003e\u003c/span\u003e\u003cscript type=\"math/tex\" id=\"MathJax-Element-17\"\u003et_i\u003c/script\u003e 和 \u003cspan class=\"MathJax_Preview\" style=\"color: inherit;\"\u003e\u003cspan class=\"MJXp-math\" id=\"MJXp-Span-88\"\u003e\u003cspan class=\"MJXp-msubsup\" id=\"MJXp-Span-89\"\u003e\u003cspan class=\"MJXp-mi MJXp-italic\" id=\"MJXp-Span-90\" style=\"margin-right: 0.05em;\"\u003em\u003c/span\u003e\u003cspan class=\"MJXp-mi MJXp-italic MJXp-script\" id=\"MJXp-Span-91\" style=\"vertical-align: -0.4em;\"\u003ei\u003c/span\u003e\u003c/span\u003e\u003c/span\u003e\u003c/span\u003e\u003cscript type=\"math/tex\" id=\"MathJax-Element-18\"\u003em_i\u003c/script\u003e。\u003c/p\u003e\u003cp\u003e其中 \u003cspan class=\"MathJax_Preview\" style=\"color: inherit;\"\u003e\u003cspan class=\"MJXp-math\" id=\"MJXp-Span-92\"\u003e\u003cspan class=\"MJXp-msubsup\" id=\"MJXp-Span-93\"\u003e\u003cspan class=\"MJXp-mi MJXp-italic\" id=\"MJXp-Span-94\" style=\"margin-right: 0.05em;\"\u003et\u003c/span\u003e\u003cspan class=\"MJXp-mi MJXp-italic MJXp-script\" id=\"MJXp-Span-95\" style=\"vertical-align: -0.4em;\"\u003ei\u003c/span\u003e\u003c/span\u003e\u003c/span\u003e\u003c/span\u003e\u003cscript type=\"math/tex\" id=\"MathJax-Element-19\"\u003et_i\u003c/script\u003e 如果是 \u003cspan class=\"MathJax_Preview\" style=\"color: inherit;\"\u003e\u003cspan class=\"MJXp-math\" id=\"MJXp-Span-96\"\u003e\u003cspan class=\"MJXp-mn\" id=\"MJXp-Span-97\"\u003e1\u003c/span\u003e\u003c/span\u003e\u003c/span\u003e\u003cscript type=\"math/tex\" id=\"MathJax-Element-20\"\u003e1\u003c/script\u003e 表示这个节点是黑色的，否则表示这个点是白色的。\u003cspan class=\"MathJax_Preview\" style=\"color: inherit;\"\u003e\u003cspan class=\"MJXp-math\" id=\"MJXp-Span-98\"\u003e\u003cspan class=\"MJXp-msubsup\" id=\"MJXp-Span-99\"\u003e\u003cspan class=\"MJXp-mi MJXp-italic\" id=\"MJXp-Span-100\" style=\"margin-right: 0.05em;\"\u003em\u003c/span\u003e\u003cspan class=\"MJXp-mi MJXp-italic MJXp-script\" id=\"MJXp-Span-101\" style=\"vertical-align: -0.4em;\"\u003ei\u003c/span\u003e\u003c/span\u003e\u003c/span\u003e\u003c/span\u003e\u003cscript type=\"math/tex\" id=\"MathJax-Element-21\"\u003em_i\u003c/script\u003e 表示建树时这个节点划分子区间的临界点，如果当前区间为 \u003cspan class=\"MathJax_Preview\" style=\"color: inherit;\"\u003e\u003cspan class=\"MJXp-math\" id=\"MJXp-Span-102\"\u003e\u003cspan class=\"MJXp-mo\" id=\"MJXp-Span-103\" style=\"margin-left: 0em; margin-right: 0em;\"\u003e[\u003c/span\u003e\u003cspan class=\"MJXp-msubsup\" id=\"MJXp-Span-104\"\u003e\u003cspan class=\"MJXp-mi MJXp-italic\" id=\"MJXp-Span-105\" style=\"margin-right: 0.05em;\"\u003el\u003c/span\u003e\u003cspan class=\"MJXp-mi MJXp-italic MJXp-script\" id=\"MJXp-Span-106\" style=\"vertical-align: -0.4em;\"\u003ei\u003c/span\u003e\u003c/span\u003e\u003cspan class=\"MJXp-mo\" id=\"MJXp-Span-107\" style=\"margin-left: 0em; margin-right: 0.222em;\"\u003e,\u003c/span\u003e\u003cspan class=\"MJXp-msubsup\" id=\"MJXp-Span-108\"\u003e\u003cspan class=\"MJXp-mi MJXp-italic\" id=\"MJXp-Span-109\" style=\"margin-right: 0.05em;\"\u003er\u003c/span\u003e\u003cspan class=\"MJXp-mi MJXp-italic MJXp-script\" id=\"MJXp-Span-110\" style=\"vertical-align: -0.4em;\"\u003ei\u003c/span\u003e\u003c/span\u003e\u003cspan class=\"MJXp-mo\" id=\"MJXp-Span-111\" style=\"margin-left: 0em; margin-right: 0em;\"\u003e]\u003c/span\u003e\u003c/span\u003e\u003c/span\u003e\u003cscript type=\"math/tex\" id=\"MathJax-Element-22\"\u003e[l_i,r_i]\u003c/script\u003e，保证 \u003cspan class=\"MathJax_Preview\" style=\"color: inherit;\"\u003e\u003cspan class=\"MJXp-math\" id=\"MJXp-Span-112\"\u003e\u003cspan class=\"MJXp-msubsup\" id=\"MJXp-Span-113\"\u003e\u003cspan class=\"MJXp-mi MJXp-italic\" id=\"MJXp-Span-114\" style=\"margin-right: 0.05em;\"\u003el\u003c/span\u003e\u003cspan class=\"MJXp-mi MJXp-italic MJXp-script\" id=\"MJXp-Span-115\" style=\"vertical-align: -0.4em;\"\u003ei\u003c/span\u003e\u003c/span\u003e\u003cspan class=\"MJXp-mo\" id=\"MJXp-Span-116\" style=\"margin-left: 0.333em; margin-right: 0.333em;\"\u003e≤\u003c/span\u003e\u003cspan class=\"MJXp-msubsup\" id=\"MJXp-Span-117\"\u003e\u003cspan class=\"MJXp-mi MJXp-italic\" id=\"MJXp-Span-118\" style=\"margin-right: 0.05em;\"\u003em\u003c/span\u003e\u003cspan class=\"MJXp-mi MJXp-italic MJXp-script\" id=\"MJXp-Span-119\" style=\"vertical-align: -0.4em;\"\u003ei\u003c/span\u003e\u003c/span\u003e\u003cspan class=\"MJXp-mo\" id=\"MJXp-Span-120\" style=\"margin-left: 0.333em; margin-right: 0.333em;\"\u003e\u0026lt;\u003c/span\u003e\u003cspan class=\"MJXp-msubsup\" id=\"MJXp-Span-121\"\u003e\u003cspan class=\"MJXp-mi MJXp-italic\" id=\"MJXp-Span-122\" style=\"margin-right: 0.05em;\"\u003er\u003c/span\u003e\u003cspan class=\"MJXp-mi MJXp-italic MJXp-script\" id=\"MJXp-Span-123\" style=\"vertical-align: -0.4em;\"\u003ei\u003c/span\u003e\u003c/span\u003e\u003c/span\u003e\u003c/span\u003e\u003cscript type=\"math/tex\" id=\"MathJax-Element-23\"\u003el_i\\leq m_i\u003c r_i\u003c/script\u003e。\u003c/p\u003e\u003cp\u003e聪明的 sylvia 发现给出这些信息是可以唯一确定一棵奇怪的线段树的，所以她决定就以这种格式来告诉你这些信息。\u003c/p\u003e",
      "misc": ""
    },
    {
      "title": "输出格式",
      "content": "\u003cp\u003e输出一行表示答案，因为 sylvia 是一个粗心的女孩子，所以可能存在无解的情况，这时只要输出 OwO 就好了。\u003c/p\u003e",
      "misc": ""
    },
    {
      "title": "限制与约定",
      "content": "\u003cp\u003e由于一些原因，本题使用捆绑测试。每个子任务有若干个测试点，分为 \u003cspan class=\"MathJax_Preview\" style=\"color: inherit;\"\u003e\u003cspan class=\"MJXp-math\" id=\"MJXp-Span-148\"\u003e\u003cspan class=\"MJXp-mn\" id=\"MJXp-Span-149\"\u003e5\u003c/span\u003e\u003c/span\u003e\u003c/span\u003e\u003cscript type=\"math/tex\" id=\"MathJax-Element-28\"\u003e5\u003c/script\u003e 个子任务，你只有通过一个子任务的所有测试点才能得到这个子任务的分数。\u003c/p\u003e\u003cdiv class=\"table-responsive\"\u003e\n\u003ctable class=\"table table-bordered table-text-center table-vertical-middle\"\u003e\u003cthead\u003e\u003ctr\u003e\u003cth\u003e子任务\u003c/th\u003e\n\u003cth\u003e分值\u003c/th\u003e\n\u003cth\u003e限制\u003c/th\u003e\n\u003c/tr\u003e\u003c/thead\u003e\u003ctbody\u003e\u003ctr\u003e\u003ctd\u003e1\u003c/td\u003e\u003ctd\u003e15\u003c/td\u003e\u003ctd\u003e\u003cspan class=\"MathJax_Preview\" style=\"color: inherit;\"\u003e\u003cspan class=\"MJXp-math\" id=\"MJXp-Span-150\"\u003e\u003cspan class=\"MJXp-mi MJXp-italic\" id=\"MJXp-Span-151\"\u003en\u003c/span\u003e\u003cspan class=\"MJXp-mo\" id=\"MJXp-Span-152\" style=\"margin-left: 0.333em; margin-right: 0.333em;\"\u003e≤\u003c/span\u003e\u003cspan class=\"MJXp-mn\" id=\"MJXp-Span-153\"\u003e10\u003c/span\u003e\u003c/span\u003e\u003c/span\u003e\u003cscript type=\"math/tex\" id=\"MathJax-Element-29\"\u003en \\leq 10\u003c/script\u003e\u003c/td\u003e\u003c/tr\u003e\u003ctr\u003e\u003ctd\u003e2\u003c/td\u003e\u003ctd\u003e15\u003c/td\u003e\u003ctd\u003e\u003cspan class=\"MathJax_Preview\" style=\"color: inherit;\"\u003e\u003cspan class=\"MJXp-math\" id=\"MJXp-Span-154\"\u003e\u003cspan class=\"MJXp-mi MJXp-italic\" id=\"MJXp-Span-155\"\u003en\u003c/span\u003e\u003cspan class=\"MJXp-mo\" id=\"MJXp-Span-156\" style=\"margin-left: 0.333em; margin-right: 0.333em;\"\u003e≤\u003c/span\u003e\u003cspan class=\"MJXp-mn\" id=\"MJXp-Span-157\"\u003e20\u003c/span\u003e\u003c/span\u003e\u003c/span\u003e\u003cscript type=\"math/tex\" id=\"MathJax-Element-30\"\u003en \\leq 20\u003c/script\u003e\u003c/td\u003e\u003c/tr\u003e\u003ctr\u003e\u003ctd\u003e3\u003c/td\u003e\u003ctd\u003e30\u003c/td\u003e\u003ctd\u003e\u003cspan class=\"MathJax_Preview\" style=\"color: inherit;\"\u003e\u003cspan class=\"MJXp-math\" id=\"MJXp-Span-158\"\u003e\u003cspan class=\"MJXp-mi MJXp-italic\" id=\"MJXp-Span-159\"\u003en\u003c/span\u003e\u003cspan class=\"MJXp-mo\" id=\"MJXp-Span-160\" style=\"margin-left: 0.333em; margin-right: 0.333em;\"\u003e≤\u003c/span\u003e\u003cspan class=\"MJXp-mn\" id=\"MJXp-Span-161\"\u003e50\u003c/span\u003e\u003c/span\u003e\u003c/span\u003e\u003cscript type=\"math/tex\" id=\"MathJax-Element-31\"\u003en \\leq 50\u003c/script\u003e\u003c/td\u003e\u003c/tr\u003e\u003ctr\u003e\u003ctd\u003e4\u003c/td\u003e\u003ctd\u003e20\u003c/td\u003e\u003ctd\u003e\u003cspan class=\"MathJax_Preview\" style=\"color: inherit;\"\u003e\u003cspan class=\"MJXp-math\" id=\"MJXp-Span-162\"\u003e\u003cspan class=\"MJXp-mi MJXp-italic\" id=\"MJXp-Span-163\"\u003en\u003c/span\u003e\u003cspan class=\"MJXp-mo\" id=\"MJXp-Span-164\" style=\"margin-left: 0.333em; margin-right: 0.333em;\"\u003e≤\u003c/span\u003e\u003cspan class=\"MJXp-mn\" id=\"MJXp-Span-165\"\u003e200\u003c/span\u003e\u003c/span\u003e\u003c/span\u003e\u003cscript type=\"math/tex\" id=\"MathJax-Element-32\"\u003en \\leq 200\u003c/script\u003e\u003c/td\u003e\u003c/tr\u003e\u003ctr\u003e\u003ctd\u003e5\u003c/td\u003e\u003ctd\u003e20\u003c/td\u003e\u003ctd\u003e\u003cspan class=\"MathJax_Preview\" style=\"color: inherit;\"\u003e\u003cspan class=\"MJXp-math\" id=\"MJXp-Span-166\"\u003e\u003cspan class=\"MJXp-mi MJXp-italic\" id=\"MJXp-Span-167\"\u003en\u003c/span\u003e\u003cspan class=\"MJXp-mo\" id=\"MJXp-Span-168\" style=\"margin-left: 0.333em; margin-right: 0.333em;\"\u003e≤\u003c/span\u003e\u003cspan class=\"MJXp-mn\" id=\"MJXp-Span-169\"\u003e4000\u003c/span\u003e\u003c/span\u003e\u003c/span\u003e\u003cscript type=\"math/tex\" id=\"MathJax-Element-33\"\u003en \\leq 4000\u003c/script\u003e\u003c/td\u003e\u003c/tr\u003e\u003c/tbody\u003e\u003c/table\u003e\u003c/div\u003e",
      "misc": ""
    },
    {
      "title": "下载",
      "content": "\u003cp\u003e\u003ca href=\"/download.php?type=problem\u0026amp;id=217\"\u003e样例数据下载\u003c/a\u003e\u003c/p\u003e",
      "misc": ""
    }
  ],
  "samples": [
    {
      "title": "样例一",
      "input": "\u003cpre\u003e2\n1 1\n1\n1\n\n\u003c/pre\u003e",
      "output": "\u003cpre\u003e2\n\n\u003c/pre\u003e",
      "explanation": "\u003cp\u003e最优解为对区间 \u003cspan class=\"MathJax_Preview\" style=\"color: inherit;\"\u003e\u003cspan class=\"MJXp-math\" id=\"MJXp-Span-124\"\u003e\u003cspan class=\"MJXp-mo\" id=\"MJXp-Span-125\" style=\"margin-left: 0em; margin-right: 0em;\"\u003e[\u003c/span\u003e\u003cspan class=\"MJXp-mn\" id=\"MJXp-Span-126\"\u003e1\u003c/span\u003e\u003cspan class=\"MJXp-mo\" id=\"MJXp-Span-127\" style=\"margin-left: 0em; margin-right: 0.222em;\"\u003e,\u003c/span\u003e\u003cspan class=\"MJXp-mn\" id=\"MJXp-Span-128\"\u003e1\u003c/span\u003e\u003cspan class=\"MJXp-mo\" id=\"MJXp-Span-129\" style=\"margin-left: 0em; margin-right: 0em;\"\u003e]\u003c/span\u003e\u003c/span\u003e\u003c/span\u003e\u003cscript type=\"math/tex\" id=\"MathJax-Element-24\"\u003e[1,1]\u003c/script\u003e 和 \u003cspan class=\"MathJax_Preview\" style=\"color: inherit;\"\u003e\u003cspan class=\"MJXp-math\" id=\"MJXp-Span-130\"\u003e\u003cspan class=\"MJXp-mo\" id=\"MJXp-Span-131\" style=\"margin-left: 0em; margin-right: 0em;\"\u003e[\u003c/span\u003e\u003cspan class=\"MJXp-mn\" id=\"MJXp-Span-132\"\u003e2\u003c/span\u003e\u003cspan class=\"MJXp-mo\" id=\"MJXp-Span-133\" style=\"margin-left: 0em; margin-right: 0.222em;\"\u003e,\u003c/span\u003e\u003cspan class=\"MJXp-mn\" id=\"MJXp-Span-134\"\u003e2\u003c/span\u003e\u003cspan class=\"MJXp-mo\" id=\"MJXp-Span-135\" style=\"margin-left: 0em; margin-right: 0em;\"\u003e]\u003c/span\u003e\u003c/span\u003e\u003c/span\u003e\u003cscript type=\"math/tex\" id=\"MathJax-Element-25\"\u003e[2,2]\u003c/script\u003e 进行操作。\u003c/p\u003e",
      "misc": ""
    },
    {
      "title": "样例二",
      "input": "\u003cpre\u003e2\n0 1\n1\n1\n\n\u003c/pre\u003e",
      "output": "\u003cpre\u003eOwO\n\n\u003c/pre\u003e",
      "explanation": "",
      "misc": ""
    },
    {
      "title": "样例三",
      "input": "\u003cpre\u003e9\n1 5\n1 3\n1 2\n1 1\n0\n1\n1\n1 4\n0\n0\n1 7\n1 6\n1\n0\n1 8\n1\n0\n\n\u003c/pre\u003e",
      "output": "\u003cpre\u003e2\n\n\u003c/pre\u003e",
      "explanation": "\u003cp\u003e最优解为对区间 \u003cspan class=\"MathJax_Preview\" style=\"color: inherit;\"\u003e\u003cspan class=\"MJXp-math\" id=\"MJXp-Span-136\"\u003e\u003cspan class=\"MJXp-mo\" id=\"MJXp-Span-137\" style=\"margin-left: 0em; margin-right: 0em;\"\u003e[\u003c/span\u003e\u003cspan class=\"MJXp-mn\" id=\"MJXp-Span-138\"\u003e2\u003c/span\u003e\u003cspan class=\"MJXp-mo\" id=\"MJXp-Span-139\" style=\"margin-left: 0em; margin-right: 0.222em;\"\u003e,\u003c/span\u003e\u003cspan class=\"MJXp-mn\" id=\"MJXp-Span-140\"\u003e8\u003c/span\u003e\u003cspan class=\"MJXp-mo\" id=\"MJXp-Span-141\" style=\"margin-left: 0em; margin-right: 0em;\"\u003e]\u003c/span\u003e\u003c/span\u003e\u003c/span\u003e\u003cscript type=\"math/tex\" id=\"MathJax-Element-26\"\u003e[2,8]\u003c/script\u003e 和 \u003cspan class=\"MathJax_Preview\" style=\"color: inherit;\"\u003e\u003cspan class=\"MJXp-math\" id=\"MJXp-Span-142\"\u003e\u003cspan class=\"MJXp-mo\" id=\"MJXp-Span-143\" style=\"margin-left: 0em; margin-right: 0em;\"\u003e[\u003c/span\u003e\u003cspan class=\"MJXp-mn\" id=\"MJXp-Span-144\"\u003e6\u003c/span\u003e\u003cspan class=\"MJXp-mo\" id=\"MJXp-Span-145\" style=\"margin-left: 0em; margin-right: 0.222em;\"\u003e,\u003c/span\u003e\u003cspan class=\"MJXp-mn\" id=\"MJXp-Span-146\"\u003e6\u003c/span\u003e\u003cspan class=\"MJXp-mo\" id=\"MJXp-Span-147\" style=\"margin-left: 0em; margin-right: 0em;\"\u003e]\u003c/span\u003e\u003c/span\u003e\u003c/span\u003e\u003cscript type=\"math/tex\" id=\"MathJax-Element-27\"\u003e[6,6]\u003c/script\u003e 进行操作。\u003c/p\u003e",
      "misc": ""
    },
    {
      "title": "样例四",
      "input": "",
      "output": "",
      "explanation": "",
      "misc": "\u003cp\u003e见样例数据下载。\u003c/p\u003e"
    }
  ],
  "tags": [
    "UOJ",
    "UNR #1"
  ],
  "rules": {
    "runtime": "1000000000",
    "memory": "268435456",
    "stack": "268435456",
    "source": "51200"
  },
  "meta": {
    "created": "2021-04-09T21:35:02.143105827+08:00",
    "updated": "2021-04-09T21:35:02.143105827+08:00",
    "checked": "2021-04-09T21:35:02.143105827+08:00"
  },
  "misc": ""
}
